README.rst
setup.cfg
setup.py
sslwireless_sms/__init__.py
sslwireless_sms/sslwireless_sms.py
sslwireless_sms.egg-info/PKG-INFO
sslwireless_sms.egg-info/SOURCES.txt
sslwireless_sms.egg-info/dependency_links.txt
sslwireless_sms.egg-info/not-zip-safe
sslwireless_sms.egg-info/requires.txt
sslwireless_sms.egg-info/top_level.txt