Metadata-Version: 1.1
Name: sslwireless-sms
Version: 0.0.3
Summary: A simple python wrapper for sslwireless sms api.
Home-page: https://github.com/rahulhaque/sslwireless-sms-wrapper-python
Author: Rahul Haque
Author-email: rahulhaque07@gmail.com
License: MIT
Download-URL: https://github.com/rahulhaque/sslwireless-sms-wrapper-python/archive/v0.0.3.tar.gz
Keywords: python,sslwireless,sms,api-wrapper
Platform: UNKNOWN
Classifier: Development Status :: 3 - Alpha
Classifier: Intended Audience :: Developers
Classifier: License :: OSI Approved :: MIT License
Classifier: Programming Language :: Python :: 2
Classifier: Programming Language :: Python :: 3
